<?xml version="1.0" encoding="UTF-8" standalone="yes"?>
<recursive-list list-id="archaeology.dcterms.temporal">
    <entry key="PALEO" shortname="Paleolithicum: tot 8800 vC" name="Paleolithicum: tot 8800 vC" ordinal="1000">
        <entry key="PALEOV" shortname="Vroeg: tot 300000 C14" name="Paleolithicum vroeg: tot 300000 C14" ordinal="1010"/>
        <entry key="PALEOM" shortname="Midden: 300000 - 35000 C14" name="Paleolithicum midden: 300000 - 35000 C14" ordinal="1020"/>
        <entry key="PALEOL" shortname="Laat: 35000 C14 - 8800 vC" name="Paleolithicum laat: 35000 C14 - 8800 vC" ordinal="1030">
	        <entry key="PALEOLA" shortname="Laat A: 35000 - 18000 C14" name="Paleolithicum laat A: 35000 - 18000 C14" ordinal="1040"/>
	        <entry key="PALEOB" shortname="Laat B: 18000 C14 -8800 vC" name="Paleolithicum laat B: 18000 C14 -8800 vC" ordinal="1050"/>
	    </entry>
    </entry>
    <entry key="MESO" shortname="Mesolithicum: 8800 - 4900 vC" name="Mesolithicum: 8800 - 4900 vC" ordinal="2000">
        <entry key="MESOV" shortname="Vroeg: 8800 - 7100 vC" name="Mesolithicum vroeg: 8800 - 7100 vC" ordinal="2010"/>
        <entry key="MESOM" shortname="Midden: 7100 - 6450 vC" name="Mesolithicum midden: 7100 - 6450 vC" ordinal="2020"/>
        <entry key="MESOL" shortname="Laat: 6450 -4900 vC" name="Mesolithicum laat: 6450 -4900 vC" ordinal="2030"/>
    </entry>
    <entry key="NEO" shortname="Neolithicum: 5300 - 2000 vC" name="Neolithicum: 5300 - 2000 vC" ordinal="3000">
        <entry key="NEOV" shortname="Vroeg: 5300 - 4200 vC" name="Neolithicum vroeg: 5300 - 4200 vC" ordinal="3010">
	        <entry key="NEOVA" shortname="Vroeg A: 5300 - 4900 vC" name="Neolithicum vroeg A: 5300 - 4900 vC" ordinal="3020"/>
	        <entry key="NEOVB" shortname="Vroeg B: 4900 - 4200 vC" name="Neolithicum vroeg B: 4900 - 4200 vC" ordinal="3030"/>
	    </entry>
        <entry key="NEOM" shortname="Midden: 4200 - 2850 vC" name="Neolithicum midden: 4200 - 2850 vC" ordinal="3040">
	        <entry key="NEOMA" shortname="Midden A: 4200 - 3400 vC" name="Neolithicum midden A: 4200 - 3400 vC" ordinal="3050"/>
	        <entry key="NEOMB" shortname="Midden B: 3400 - 2850 vC" name="Neolithicum midden B: 3400 - 2850 vC" ordinal="3060"/>
	    </entry>
        <entry key="NEOL" shortname="Laat: 2850 - 2000 vC" name="Neolithicum laat: 2850 - 2000 vC" ordinal="3070">
	        <entry key="NEOLA" shortname="Laat A: 2850 - 2450 vC" name="Neolithicum laat A: 2850 - 2450 vC" ordinal="3080"/>
	        <entry key="NEOLB" shortname="Laat B: 2450 - 2000 vC" name="Neolithicum laat B: 2450 - 2000 vC" ordinal="3090"/>
	    </entry>
    </entry>
    <entry key="BRONS" shortname="Bronstijd: 2000 - 800 vC" name="Bronstijd: 2000 - 800 vC" ordinal="4000">
        <entry key="BRONSV" shortname="Vroeg: 2000 - 1800 vC" name="Bronstijd vroeg: 2000 - 1800 vC" ordinal="4010"/>
        <entry key="BRONSM" shortname="Midden: 1800 - 1100 vC" name="Bronstijd midden: 1800 - 1100 vC" ordinal="4020">
	        <entry key="BRONSMA" shortname="Midden A: 1800 - 1500 vC" name="Bronstijd midden A: 1800 - 1500 vC" ordinal="4030"/>
	        <entry key="BRONSMB" shortname="Midden B: 1500 - 1100 vC" name="Bronstijd midden B: 1500 - 1100 vC" ordinal="4040"/>
	    </entry>
        <entry key="BRONSL" shortname="Laat: 1100 - 800 vC" name="Bronstijd laat: 1100 - 800 vC" ordinal="4050"/>
    </entry>
    <entry key="IJZ" shortname="IJzertijd: 800 - 12 vC" name="IJzertijd: 800 - 12 vC" ordinal="5000">
        <entry key="IJZV" shortname="Vroeg: 800 - 500 vC" name="IJzertijd vroeg: 800 - 500 vC" ordinal="5010"/>
        <entry key="IJZM" shortname="Midden: 500 - 250 vC" name="IJzertijd midden: 500 - 250 vC" ordinal="5020"/>
        <entry key="IJZL" shortname="Laat: 250 - 12 vC" name="IJzertijd laat: 250 - 12 vC" ordinal="5030"/>
    </entry>
    <entry key="ROM" shortname="Romeinse tijd: 12 vC - 450 nC" name="Romeinse tijd: 12 vC - 450 nC" ordinal="6000">
        <entry key="ROMV" shortname="Vroeg: 12 vC - 70 nC" name="Romeinse tijd vroeg: 12 vC - 70 nC" ordinal="6010">
	        <entry key="ROMVA" shortname="Vroeg A: 12 vC - 25 nC" name="Romeinse tijd vroeg A: 12 vC - 25 nC" ordinal="6020"/>
	        <entry key="ROMVB" shortname="Vroeg B: 25 - 70 nC" name="Romeinse tijd vroeg B: 25 - 70 nC" ordinal="6030"/>
	    </entry>
        <entry key="ROMM" shortname="Midden: 70 - 270 nC" name="Romeinse tijd midden: 70 - 270 nC" ordinal="6040">
	        <entry key="ROMMA" shortname="Midden A: 70 - 150 nC" name="Romeinse tijd midden A: 70 - 150 nC" ordinal="6050"/>
	        <entry key="ROMMB" shortname="Midden B: 150 - 270 nC" name="Romeinse tijd midden B: 150 - 270 nC" ordinal="6060"/>
	    </entry>
        <entry key="ROML" shortname="Laat: 270 - 450 nC" name="Romeinse tijd laat: 270 - 450 nC" ordinal="6070">
	        <entry key="ROMLA" shortname="Laat A: 270 - 350 nC" name="Romeinse tijd laat A: 270 - 350 nC" ordinal="6080"/>
	        <entry key="ROMLB" shortname="Laat B: 350 - 450 nC" name="Romeinse tijd laat B: 350 - 450 nC" ordinal="6090"/>
	    </entry>
    </entry>
    <entry key="XME" shortname="Middeleeuwen: 450 - 1500 nC" name="Middeleeuwen: 450 - 1500 nC" ordinal="7000">
        <entry key="VME" shortname="Vroeg: 450 - 1050 nC" name="Middeleeuwen vroeg: 450 - 1050 nC" ordinal="7010">
	        <entry key="VMEA" shortname="Vroeg A: 450 - 525 nC" name="Middeleeuwen vroeg A: 450 - 525 nC" ordinal="7020"/>
	        <entry key="VMEB" shortname="Vroeg B: 525 - 725 nC" name="Middeleeuwen vroeg B: 525 - 725 nC" ordinal="7030"/>
	        <entry key="VMEC" shortname="Vroeg C: 725 - 900 nC" name="Middeleeuwen vroeg C: 725 - 900 nC" ordinal="7040"/>
	        <entry key="VMED" shortname="Vroeg D: 900 - 1050 nC" name="Middeleeuwen vroeg D: 900 - 1050 nC" ordinal="7050"/>
	    </entry>
        <entry key="LME" shortname="Laat: 1050 - 1500 nC" name="Middeleeuwen laat: 1050 - 1500 nC" ordinal="7060">
	        <entry key="LMEA" shortname="Laat A: 1050 - 1250 nC" name="Middeleeuwen laat A: 1050 - 1250 nC" ordinal="7070"/>
	        <entry key="LMEB" shortname="Laat B: 1250 - 1500 nC" name="Middeleeuwen laat B: 1250 - 1500 nC" ordinal="7080"/>
	    </entry>
    </entry>
    <entry key="NT" shortname="Nieuwe tijd: 1500 - heden" name="Nieuwe tijd: 1500 - heden" ordinal="8000">
        <entry key="NTA" shortname="Nieuwe tijd A: 1500 - 1650 nC" name="Nieuwe tijd A: 1500 - 1650 nC" ordinal="8010"/>
        <entry key="NTB" shortname="Nieuwe tijd B: 1650 - 1850 nC" name="Nieuwe tijd B: 1650 - 1850 nC" ordinal="8020"/>
        <entry key="NTC" shortname="Nieuwe tijd C: 1850 - heden" name="Nieuwe tijd C: 1850 - heden" ordinal="8030"/>
    </entry>
    <entry key="XXX" shortname="Onbekend" name="Onbekend" ordinal="9999"/>
</recursive-list>